[
    {
        "timestamp": "2024-11-07T13:46:24.611997",
        "message": "Activision ID Roles Bot#8980 has connected to Discord!"
    },
    {
        "timestamp": "2024-11-07T13:49:20.450735",
        "message": "Activision ID Roles Bot#8980 has connected to Discord!"
    },
    {
        "timestamp": "2024-11-07T13:49:20.598117",
        "message": "Bot is ready!"
    },
    {
        "timestamp": "2024-11-07T13:50:10.767402",
        "message": "Activision ID Roles Bot#8980 has connected to Discord!"
    },
    {
        "timestamp": "2024-11-07T13:50:10.919614",
        "message": "Bot is ready!"
    },
    {
        "timestamp": "2024-11-07T13:50:52.207509",
        "message": "Activision ID Roles Bot#8980 has connected to Discord!"
    },
    {
        "timestamp": "2024-11-07T13:50:52.322983",
        "message": "Bot is ready!"
    },
    {
        "timestamp": "2024-11-07T13:51:39.606270",
        "message": "Activision ID Roles Bot#8980 has connected to Discord!"
    },
    {
        "timestamp": "2024-11-07T13:51:39.727574",
        "message": "Bot is ready!"
    },
    {
        "timestamp": "2024-11-07T13:52:22.166127",
        "message": "thetruehighking: got Activision ID Roles Bot#8980's ID  <Placeholder>"
    },
    {
        "timestamp": "2024-11-07T13:56:05.055448",
        "message": "Activision ID Roles Bot#8980 has connected to Discord!"
    },
    {
        "timestamp": "2024-11-07T13:56:05.196072",
        "message": "Bot is ready!"
    },
    {
        "timestamp": "2024-11-07T13:57:07.785322",
        "message": "Activision ID Roles Bot#8980 has connected to Discord!"
    },
    {
        "timestamp": "2024-11-07T13:57:07.906137",
        "message": "Bot is ready!"
    },
    {
        "timestamp": "2024-11-07T13:57:34.157311",
        "message": "Activision ID Roles Bot#8980 has connected to Discord!"
    },
    {
        "timestamp": "2024-11-07T13:58:07.915224",
        "message": "Bot is ready!"
    },
    {
        "timestamp": "2024-11-07T13:59:29.101291",
        "message": "Activision ID Roles Bot#8980 has connected to Discord!"
    },
    {
        "timestamp": "2024-11-07T13:59:29.328216",
        "message": "Bot is ready!"
    },
    {
        "timestamp": "2024-11-07T14:03:01.116496",
        "message": "Activision ID Roles Bot#8980 has connected to Discord!"
    },
    {
        "timestamp": "2024-11-07T14:03:01.242644",
        "message": "Bot is ready!"
    },
    {
        "timestamp": "2024-11-07T14:03:23.620360",
        "message": "Activision ID Roles Bot#8980 has connected to Discord!"
    },
    {
        "timestamp": "2024-11-07T14:04:01.225257",
        "message": "Bot is ready!"
    },
    {
        "timestamp": "2024-11-07T14:04:28.361284",
        "message": "Activision ID Roles Bot#8980 has connected to Discord!"
    },
    {
        "timestamp": "2024-11-07T14:04:28.578265",
        "message": "Bot is ready!"
    },
    {
        "timestamp": "2024-11-07T14:05:49.857027",
        "message": "Activision ID Roles Bot#8980 has connected to Discord!"
    },
    {
        "timestamp": "2024-11-07T14:05:49.981860",
        "message": "Bot is ready!"
    },
    {
        "timestamp": "2024-11-07T14:07:36.904679",
        "message": "Activision ID Roles Bot#8980 has connected to Discord!"
    },
    {
        "timestamp": "2024-11-07T14:07:37.060855",
        "message": "Bot is ready!"
    },
    {
        "timestamp": "2024-11-07T14:08:08.294788",
        "message": "Activision ID Roles Bot#8980 has connected to Discord!"
    },
    {
        "timestamp": "2024-11-07T14:08:08.435189",
        "message": "Bot is ready!"
    },
    {
        "timestamp": "2024-11-07T14:14:25.130608",
        "message": "Activision ID Roles Bot#8980 has connected to Discord!"
    },
    {
        "timestamp": "2024-11-07T14:14:25.233680",
        "message": "Bot is ready!"
    },
    {
        "timestamp": "2024-11-07T14:16:32.103990",
        "message": "Activision ID Roles Bot#8980 has connected to Discord!"
    },
    {
        "timestamp": "2024-11-07T14:16:32.227098",
        "message": "Bot is ready!"
    },
    {
        "timestamp": "2024-11-07T14:17:43.214507",
        "message": "Activision ID Roles Bot#8980 has connected to Discord!"
    },
    {
        "timestamp": "2024-11-07T14:17:43.418486",
        "message": "Bot is ready!"
    },
    {
        "timestamp": "2024-11-07T14:21:24.921035",
        "message": "Activision ID Roles Bot#8980 has connected to Discord!"
    },
    {
        "timestamp": "2024-11-07T14:21:25.048648",
        "message": "Bot is ready!"
    },
    {
        "timestamp": "2024-11-07T14:25:50.812962",
        "message": "Activision ID Roles Bot#8980 has connected to Discord!"
    },
    {
        "timestamp": "2024-11-07T14:25:50.929143",
        "message": "Bot is ready!"
    },
    {
        "timestamp": "2024-11-07T14:27:16.869872",
        "message": "Activision ID Roles Bot#8980 has connected to Discord!"
    },
    {
        "timestamp": "2024-11-07T14:27:17.016047",
        "message": "Bot is ready!"
    },
    {
        "timestamp": "2024-11-07T14:30:27.622914",
        "message": "Succesfuly connected to MongoDB"
    },
    {
        "timestamp": "2024-11-07T14:30:30.396691",
        "message": "Activision ID Roles Bot#8980 has connected to Discord!"
    },
    {
        "timestamp": "2024-11-07T14:30:30.502340",
        "message": "Bot is ready!"
    },
    {
        "timestamp": "2024-11-07T14:30:38.314762",
        "message": "I inserted 672d074df01b00ec0c04b4cb documents."
    },
    {
        "timestamp": "2024-11-07T14:33:44.441290",
        "message": "Succesfuly connected to MongoDB"
    },
    {
        "timestamp": "2024-11-07T14:33:47.095678",
        "message": "Activision ID Roles Bot#8980 has connected to Discord!"
    },
    {
        "timestamp": "2024-11-07T14:33:47.233393",
        "message": "Bot is ready!"
    },
    {
        "timestamp": "2024-11-07T14:34:27.416057",
        "message": "Succesfuly connected to MongoDB"
    },
    {
        "timestamp": "2024-11-07T14:34:30.148700",
        "message": "Activision ID Roles Bot#8980 has connected to Discord!"
    },
    {
        "timestamp": "2024-11-07T14:34:30.271602",
        "message": "Bot is ready!"
    },
    {
        "timestamp": "2024-11-07T14:42:11.269464",
        "message": "Succesfuly connected to MongoDB"
    },
    {
        "timestamp": "2024-11-07T14:42:13.896868",
        "message": "Activision ID Roles Bot#8980 has connected to Discord!"
    },
    {
        "timestamp": "2024-11-07T14:42:14.020977",
        "message": "Bot is ready!"
    },
    {
        "timestamp": "2024-11-07T14:42:24.769393",
        "message": "I inserted 672d0a105a12e125e539bf62 documents."
    },
    {
        "timestamp": "2024-11-07T14:44:35.591549",
        "message": "Succesfuly connected to MongoDB"
    },
    {
        "timestamp": "2024-11-07T14:44:38.210365",
        "message": "Activision ID Roles Bot#8980 has connected to Discord!"
    },
    {
        "timestamp": "2024-11-07T14:44:48.710032",
        "message": "Succesfuly connected to MongoDB"
    },
    {
        "timestamp": "2024-11-07T14:44:51.242244",
        "message": "Activision ID Roles Bot#8980 has connected to Discord!"
    },
    {
        "timestamp": "2024-11-07T14:45:02.644909",
        "message": "I inserted 672d0aaee6ea8386b4e688a9 documents."
    },
    {
        "timestamp": "2024-11-07T14:45:16.989816",
        "message": "Succesfuly connected to MongoDB"
    },
    {
        "timestamp": "2024-11-07T14:45:19.570970",
        "message": "Activision ID Roles Bot#8980 has connected to Discord!"
    },
    {
        "timestamp": "2024-11-07T14:46:18.742219",
        "message": "Succesfuly connected to MongoDB"
    },
    {
        "timestamp": "2024-11-07T14:46:21.329532",
        "message": "Activision ID Roles Bot#8980 has connected to Discord!"
    },
    {
        "timestamp": "2024-11-07T14:46:21.486942",
        "message": "Bot is ready!"
    },
    {
        "timestamp": "2024-11-07T14:46:36.671245",
        "message": "Succesfuly connected to MongoDB"
    },
    {
        "timestamp": "2024-11-07T14:46:39.243571",
        "message": "Activision ID Roles Bot#8980 has connected to Discord!"
    },
    {
        "timestamp": "2024-11-07T14:46:54.185263",
        "message": "I inserted 672d0b1d885a66b2228449da documents."
    },
    {
        "timestamp": "2024-11-07T14:47:21.476151",
        "message": "Bot is ready!"
    },
    {
        "timestamp": "2024-11-07T14:47:58.887101",
        "message": "Succesfuly connected to MongoDB"
    },
    {
        "timestamp": "2024-11-07T14:48:01.723673",
        "message": "Activision ID Roles Bot#8980 has connected to Discord!"
    },
    {
        "timestamp": "2024-11-07T14:48:01.963520",
        "message": "Bot is ready!"
    },
    {
        "timestamp": "2024-11-07T14:48:45.026990",
        "message": "Succesfuly connected to MongoDB"
    },
    {
        "timestamp": "2024-11-07T14:48:47.791049",
        "message": "Activision ID Roles Bot#8980 has connected to Discord!"
    },
    {
        "timestamp": "2024-11-07T14:48:47.915828",
        "message": "Bot is ready!"
    },
    {
        "timestamp": "2024-11-07T14:48:57.196190",
        "message": "I inserted 672d0b985d4f93b7af4b3abd documents."
    },
    {
        "timestamp": "2024-11-07T14:55:46.963179",
        "message": "I inserted 672d0d325d4f93b7af4b3abe documents."
    },
    {
        "timestamp": "2024-11-07T14:55:51.540572",
        "message": "Succesfuly connected to MongoDB"
    },
    {
        "timestamp": "2024-11-07T14:55:54.278167",
        "message": "Activision ID Roles Bot#8980 has connected to Discord!"
    },
    {
        "timestamp": "2024-11-07T14:55:54.445177",
        "message": "Bot is ready!"
    },
    {
        "timestamp": "2024-11-07T14:56:45.639993",
        "message": "Succesfuly connected to MongoDB"
    },
    {
        "timestamp": "2024-11-07T14:56:48.157903",
        "message": "Activision ID Roles Bot#8980 has connected to Discord!"
    },
    {
        "timestamp": "2024-11-07T14:56:48.269231",
        "message": "Bot is ready!"
    }
]